[1,["1c0367fbb"],["_textureSetter"],["cc.SpriteFrame"],0,[[[{"name":"btn_add","rect":[543,74,57,56],"offset":[0,0],"originalSize":[57,56],"capInsets":[0,0,0,0]}],[0],0,[0],[0],[0]],[[{"name":"shuye2","rect":[585,190,20,15],"offset":[0,0],"originalSize":[20,15],"rotated":1,"capInsets":[0,0,0,0]}],[0],0,[0],[0],[0]],[[{"name":"guang","rect":[3,917,95,110],"offset":[0,0],"originalSize":[95,110],"rotated":1,"capInsets":[0,0,0,0]}],[0],0,[0],[0],[0]],[[{"name":"huaban","rect":[497,362,200,94],"offset":[0,0],"originalSize":[200,94],"rotated":1,"capInsets":[0,0,0,0]}],[0],0,[0],[0],[0]],[[{"name":"shuye1","rect":[543,229,29,18],"offset":[0,0],"originalSize":[29,18],"capInsets":[0,0,0,0]}],[0],0,[0],[0],[0]],[[{"name":"image_xxc","rect":[497,568,221,62],"offset":[0,0],"originalSize":[221,62],"rotated":1,"capInsets":[0,0,0,0]}],[0],0,[0],[0],[0]],[[{"name":"dikuang","rect":[3,3,215,412],"offset":[0,0],"originalSize":[215,412],"rotated":1,"capInsets":[0,0,0,0]}],[0],0,[0],[0],[0]],[[{"name":"puke","rect":[119,829,184,190],"offset":[0,0],"originalSize":[184,190],"capInsets":[0,0,0,0]}],[0],0,[0],[0],[0]],[[{"name":"zhadan","rect":[543,3,54,65],"offset":[0,0],"originalSize":[54,65],"capInsets":[0,0,0,0]}],[0],0,[0],[0],[0]],[[{"name":"zhadan","rect":[465,917,105,98],"offset":[0,0],"originalSize":[105,98],"capInsets":[0,0,0,0]}],[0],0,[0],[0],[0]],[[{"name":"dikuang","rect":[3,224,215,412],"offset":[0,0],"originalSize":[215,412],"rotated":1,"capInsets":[0,0,0,0]}],[0],0,[0],[0],[0]],[[{"name":"pai_3","rect":[497,795,95,116],"offset":[0,0],"originalSize":[95,116],"capInsets":[0,0,0,0]}],[0],0,[0],[0],[0]],[[{"name":"image_fh","rect":[543,136,57,48],"offset":[0,0],"originalSize":[57,48],"capInsets":[0,0,0,0]}],[0],0,[0],[0],[0]],[[{"name":"guang","rect":[543,190,36,33],"offset":[0,0],"originalSize":[36,33],"capInsets":[0,0,0,0]}],[0],0,[0],[0],[0]],[[{"name":"pai_4","rect":[142,666,125,136],"offset":[0,0],"originalSize":[125,136],"capInsets":[0,0,0,0]}],[0],0,[0],[0],[0]],[[{"name":"majiang","rect":[309,829,185,150],"offset":[0,0],"originalSize":[185,150],"rotated":1,"capInsets":[0,0,0,0]}],[0],0,[0],[0],[0]],[[{"name":"pai_1","rect":[3,666,133,140],"offset":[0,0],"originalSize":[133,140],"capInsets":[0,0,0,0]}],[0],0,[0],[0],[0]],[[{"name":"pai_2","rect":[273,666,113,129],"offset":[0,0],"originalSize":[113,129],"rotated":1,"capInsets":[0,0,0,0]}],[0],0,[0],[0],[0]],[[{"name":"image_dk","rect":[421,362,461,70],"offset":[0,0],"originalSize":[461,70],"rotated":1,"capInsets":[0,0,0,0]}],[0],0,[0],[0],[0]],[[{"name":"dikuang","rect":[3,445,215,412],"offset":[0,0],"originalSize":[215,412],"rotated":1,"capInsets":[0,0,0,0]}],[0],0,[0],[0],[0]],[[{"name":"btn_pipei","rect":[421,3,353,116],"offset":[0,0],"originalSize":[353,116],"rotated":1,"capInsets":[0,0,0,0]}],[0],0,[0],[0],[0]]]]